gym_wofost/__init__.py
gym_wofost/default_data/WLP_NPK.conf
gym_wofost/default_data/agro.yaml
gym_wofost/default_data/crop.cab
gym_wofost/default_data/site.cab
gym_wofost/default_data/soil.cab
gym_wofost/envs/__init__.py
gym_wofost/envs/actions.py
gym_wofost/envs/models.py
gym_wofost/envs/reward.py
gym_wofost/envs/wofost_env.py
gym_wofost-1.0.7.dist-info/METADATA
gym_wofost-1.0.7.dist-info/WHEEL
gym_wofost-1.0.7.dist-info/top_level.txt
gym_wofost-1.0.7.dist-info/RECORD
