Metadata-Version: 2.1
Name: gym-wofost
Version: 1.0.7
Summary: gym_wofost : A crop growth simulation model turn into OpenAI Gym environment
Author: AgriEdge (Noureddine Ech-chouky)
Author-email: <noureddine.echchuky@um5r.ac.ma>
License: UNKNOWN
Keywords: python,Reinforcement learning,gym environment,pcse,crop management,precision agriculture,wofost
Platform: UNKNOWN
Classifier: Development Status :: 1 - Planning
Classifier: Intended Audience :: Developers
Classifier: Programming Language :: Python :: 3.8
Classifier: Operating System :: Unix
Classifier: Operating System :: MacOS :: MacOS X
Classifier: Operating System :: Microsoft :: Windows
Requires-Dist: gym
Requires-Dist: PCSE (==5.4.2)
Requires-Dist: shutup
